amqtt/__init__.py
amqtt/adapters.py
amqtt/broker.py
amqtt/client.py
amqtt/codecs.py
amqtt/errors.py
amqtt/mqtt/__init__.py
amqtt/mqtt/connack.py
amqtt/mqtt/connect.py
amqtt/mqtt/constants.py
amqtt/mqtt/disconnect.py
amqtt/mqtt/packet.py
amqtt/mqtt/pingreq.py
amqtt/mqtt/pingresp.py
amqtt/mqtt/protocol/__init__.py
amqtt/mqtt/protocol/broker_handler.py
amqtt/mqtt/protocol/client_handler.py
amqtt/mqtt/protocol/handler.py
amqtt/mqtt/puback.py
amqtt/mqtt/pubcomp.py
amqtt/mqtt/publish.py
amqtt/mqtt/pubrec.py
amqtt/mqtt/pubrel.py
amqtt/mqtt/suback.py
amqtt/mqtt/subscribe.py
amqtt/mqtt/unsuback.py
amqtt/mqtt/unsubscribe.py
amqtt/plugins/__init__.py
amqtt/plugins/authentication.py
amqtt/plugins/logging.py
amqtt/plugins/manager.py
amqtt/plugins/persistence.py
amqtt/plugins/sys/__init__.py
amqtt/plugins/sys/broker.py
amqtt/plugins/topic_checking.py
amqtt/scripts/__init__.py
amqtt/scripts/broker_script.py
amqtt/scripts/default_broker.yaml
amqtt/scripts/default_client.yaml
amqtt/scripts/pub_script.py
amqtt/scripts/sub_script.py
amqtt/session.py
amqtt/utils.py
amqtt/version.py
hbmqtt/__init__.py
hbmqtt/adapters.py
hbmqtt/broker.py
hbmqtt/client.py
hbmqtt/codecs.py
hbmqtt/errors.py
hbmqtt/mqtt/__init__.py
hbmqtt/mqtt/connack.py
hbmqtt/mqtt/connect.py
hbmqtt/mqtt/constants.py
hbmqtt/mqtt/disconnect.py
hbmqtt/mqtt/packet.py
hbmqtt/mqtt/pingreq.py
hbmqtt/mqtt/pingresp.py
hbmqtt/mqtt/protocol/__init__.py
hbmqtt/mqtt/protocol/broker_handler.py
hbmqtt/mqtt/protocol/client_handler.py
hbmqtt/mqtt/protocol/handler.py
hbmqtt/mqtt/puback.py
hbmqtt/mqtt/pubcomp.py
hbmqtt/mqtt/publish.py
hbmqtt/mqtt/pubrec.py
hbmqtt/mqtt/pubrel.py
hbmqtt/mqtt/suback.py
hbmqtt/mqtt/subscribe.py
hbmqtt/mqtt/unsuback.py
hbmqtt/mqtt/unsubscribe.py
hbmqtt/plugins/__init__.py
hbmqtt/plugins/authentication.py
hbmqtt/plugins/logging.py
hbmqtt/plugins/manager.py
hbmqtt/plugins/persistence.py
hbmqtt/plugins/sys/__init__.py
hbmqtt/plugins/sys/broker.py
hbmqtt/plugins/topic_checking.py
hbmqtt/scripts/__init__.py
amqtt_pazzarpj-0.10.1.dev1.dist-info/entry_points.txt
amqtt_pazzarpj-0.10.1.dev1.dist-info/WHEEL
amqtt_pazzarpj-0.10.1.dev1.dist-info/METADATA
amqtt_pazzarpj-0.10.1.dev1.dist-info/RECORD
